pyfoundt/__init__.py
pyfoundt/setplt.py
pyfoundt/useragents.py
pyfoundt-0.8.1.dist-info/LICENSE.txt
pyfoundt-0.8.1.dist-info/METADATA
pyfoundt-0.8.1.dist-info/WHEEL
pyfoundt-0.8.1.dist-info/top_level.txt
pyfoundt-0.8.1.dist-info/RECORD
