Metadata-Version: 2.1
Name: pyfoundt
Version: 0.8.1
Summary: 一个普通的模块
Author: ZuoYihan(左易晗)[china(中国)]
Platform: Windows
Platform: Linux
Classifier: License :: OSI Approved :: GNU General Public License (GPL)
Requires-Python: >=3
License-File: LICENSE.txt
Requires-Dist: requests
